[{"id":1,"surname":"Ivanov","name":"Vasya","secondName":"Ivanov","address":"First Str","cardNumber":12345,"cardBalance":0},{"id":2,"surname":"Petrov","name":"Ivan","secondName":"Maksimov","address":"Second Str","cardNumber":12435,"cardBalance":10000},{"id":3,"surname":"Shevchenko","name":"Vasya","secondName":"Petrovich","address":"Third Str","cardNumber":54321,"cardBalance":723},{"id":4,"surname":"Ivanova","name":"Victoria","secondName":"Oleksiivna","address":"Fourth Str","cardNumber":24257,"cardBalance":-584},{"id":5,"surname":"Ivanov","name":"Petya","secondName":"Vladymirovich","address":"First Str","cardNumber":93841,"cardBalance":-50000}]